tqdm_logging_wrapper.py
tqdm_logging_wrapper-1.0.1.dist-info/LICENSE
tqdm_logging_wrapper-1.0.1.dist-info/METADATA
tqdm_logging_wrapper-1.0.1.dist-info/WHEEL
tqdm_logging_wrapper-1.0.1.dist-info/top_level.txt
tqdm_logging_wrapper-1.0.1.dist-info/RECORD
