Metadata-Version: 2.1
Name: tqdm-logging-wrapper
Version: 1.0.1
Summary: Wrap standard-library logging to support TQDM progress-bars.
Home-page: https://github.com/EpicWink/tqdm-logging-wrapper
Author: Laurie
Author-email: laurie_opperman@hotmail.com
License: "MIT"
Platform: UNKNOWN
Requires-Python: ~=3.6
